afterbasics/__init__.py
afterbasics/afterbasic.py
afterbasics-0.0.5.dist-info/LICENSE
afterbasics-0.0.5.dist-info/METADATA
afterbasics-0.0.5.dist-info/WHEEL
afterbasics-0.0.5.dist-info/top_level.txt
afterbasics-0.0.5.dist-info/RECORD
