Metadata-Version: 2.1
Name: afterbasics
Version: 0.0.5
Summary: Python Learning Plan WebApp- After Basics
Author: Dan Hennessy
License: UNKNOWN
Platform: UNKNOWN
Classifier: Programming Language :: Python :: 3
Classifier: License :: OSI Approved :: MIT License
Classifier: Operating System :: OS Independent
License-File: LICENSE
Requires-Dist: requests (>=2)
Provides-Extra: dev
Requires-Dist: pytest (>=6.0pytest-cov>=2.0mypy>=0.910flake8>=3.9) ; extra == 'dev'
